odoo/addons/web_help/README.rst
odoo/addons/web_help/__init__.py
odoo/addons/web_help/__manifest__.py
odoo/addons/web_help/i18n/es.po
odoo/addons/web_help/i18n/hr.po
odoo/addons/web_help/i18n/it.po
odoo/addons/web_help/i18n/web_help.pot
odoo/addons/web_help/readme/CONTRIBUTORS.rst
odoo/addons/web_help/readme/DESCRIPTION.rst
odoo/addons/web_help/readme/ROADMAP.rst
odoo/addons/web_help/readme/USAGE.rst
odoo/addons/web_help/static/description/changepassword.png
odoo/addons/web_help/static/description/demo.gif
odoo/addons/web_help/static/description/icon.png
odoo/addons/web_help/static/description/index.html
odoo/addons/web_help/static/description/viewswitcher.png
odoo/addons/web_help/static/src/change_password_trip.esm.js
odoo/addons/web_help/static/src/helpers.esm.js
odoo/addons/web_help/static/src/trip.esm.js
odoo/addons/web_help/static/src/trip.xml
odoo/addons/web_help/static/src/user_trip.esm.js
odoo/addons/web_help/static/src/components/help_button/help_button.esm.js
odoo/addons/web_help/static/src/components/help_button/help_button.xml
odoo/addons/web_help/static/src/components/highlighter/highlighter.esm.js
odoo/addons/web_help/static/src/components/highlighter/highlighter.scss
odoo/addons/web_help/static/src/components/highlighter/highlighter.xml
odoo_addon_web_help-16.0.2.0.1.dist-info/METADATA
odoo_addon_web_help-16.0.2.0.1.dist-info/WHEEL
odoo_addon_web_help-16.0.2.0.1.dist-info/top_level.txt
odoo_addon_web_help-16.0.2.0.1.dist-info/RECORD
